dataflow/__init__.py
dataflow/cli.py
dataflow/decorators.py
dataflow/exceptions.py
dataflow/gateway_integration.py
dataflow/adapters/__init__.py
dataflow/adapters/base.py
dataflow/adapters/base_adapter.py
dataflow/adapters/connection_parser.py
dataflow/adapters/exceptions.py
dataflow/adapters/factory.py
dataflow/adapters/mongodb.py
dataflow/adapters/mysql.py
dataflow/adapters/postgresql.py
dataflow/adapters/postgresql_vector.py
dataflow/adapters/sql_dialects.py
dataflow/adapters/sqlite.py
dataflow/adapters/sqlite_enterprise.py
dataflow/cache/__init__.py
dataflow/cache/async_redis_adapter.py
dataflow/cache/auto_detection.py
dataflow/cache/invalidation.py
dataflow/cache/key_generator.py
dataflow/cache/list_node_integration.py
dataflow/cache/memory_cache.py
dataflow/cache/redis_manager.py
dataflow/cli/__init__.py
dataflow/cli/analyze.py
dataflow/cli/commands.py
dataflow/cli/debug.py
dataflow/cli/debug_agent_cli.py
dataflow/cli/generate.py
dataflow/cli/inspector_cli.py
dataflow/cli/main.py
dataflow/cli/output.py
dataflow/cli/perf.py
dataflow/cli/validate.py
dataflow/compatibility/__init__.py
dataflow/compatibility/legacy_support.py
dataflow/compatibility/migration_path.py
dataflow/configuration/__init__.py
dataflow/configuration/progressive_disclosure.py
dataflow/core/__init__.py
dataflow/core/async_utils.py
dataflow/core/audit_events.py
dataflow/core/audit_integration.py
dataflow/core/audit_trail_manager.py
dataflow/core/config.py
dataflow/core/connection_pool.py
dataflow/core/database_registry.py
dataflow/core/engine.py
dataflow/core/engine_production.py
dataflow/core/error_enhancer.py
dataflow/core/model_registry.py
dataflow/core/models.py
dataflow/core/multi_tenancy.py
dataflow/core/nodes.py
dataflow/core/protected_engine.py
dataflow/core/protection.py
dataflow/core/protection_middleware.py
dataflow/core/query_router.py
dataflow/core/schema.py
dataflow/core/schema_cache.py
dataflow/core/schema_comparator.py
dataflow/core/tenant_migration.py
kailash_dataflow-0.10.16.dist-info/licenses/LICENSE
kailash_dataflow-0.10.16.dist-info/licenses/NOTICE
kailash_dataflow-0.10.16.dist-info/METADATA
kailash_dataflow-0.10.16.dist-info/WHEEL
kailash_dataflow-0.10.16.dist-info/entry_points.txt
kailash_dataflow-0.10.16.dist-info/top_level.txt
kailash_dataflow-0.10.16.dist-info/RECORD
