Metadata-Version: 2.4
Name: kailash-dataflow
Version: 0.10.16
Summary: Workflow-native database framework for Kailash SDK
Home-page: https://github.com/Integrum-Global/kailash_python_sdk
Author: Integrum
Author-email: Integrum <info@integrum.com>
License: Apache-2.0 WITH Additional-Terms
Project-URL: Homepage, https://github.com/Integrum-Global/kailash_python_sdk
Project-URL: Repository, https://github.com/Integrum-Global/kailash_python_sdk
Project-URL: Issues, https://github.com/Integrum-Global/kailash_python_sdk/issues
Classifier: Development Status :: 4 - Beta
Classifier: Intended Audience :: Developers
Classifier: Topic :: Software Development :: Libraries :: Python Modules
Classifier: License :: OSI Approved :: Apache Software License
Classifier: Programming Language :: Python :: 3
Classifier: Programming Language :: Python :: 3.11
Classifier: Programming Language :: Python :: 3.12
Classifier: Programming Language :: Python :: 3.13
Requires-Python: >=3.11
License-File: LICENSE
License-File: NOTICE
Requires-Dist: kailash>=0.10.15
Requires-Dist: sqlalchemy>=2.0.0
Requires-Dist: alembic>=1.12.0
Requires-Dist: asyncpg>=0.28.0
Requires-Dist: aiosqlite>=0.19.0
Requires-Dist: aiomysql>=0.2.0
Requires-Dist: redis>=4.5.0
Requires-Dist: pydantic>=2.0.0
Requires-Dist: click>=8.0.0
Provides-Extra: dev
Requires-Dist: pytest>=7.0.0; extra == "dev"
Requires-Dist: pytest-asyncio>=0.23.0; extra == "dev"
Requires-Dist: pytest-cov>=4.0.0; extra == "dev"
Requires-Dist: black>=23.0.0; extra == "dev"
Requires-Dist: isort>=5.12.0; extra == "dev"
Requires-Dist: flake8>=6.0.0; extra == "dev"
Requires-Dist: mypy>=1.0.0; extra == "dev"
Provides-Extra: api
Requires-Dist: fastapi>=0.104.0; extra == "api"
Requires-Dist: uvicorn[standard]>=0.24.0; extra == "api"
Requires-Dist: python-jose[cryptography]>=3.3.0; extra == "api"
Requires-Dist: passlib[bcrypt]>=1.7.4; extra == "api"
Provides-Extra: enterprise
Requires-Dist: cryptography>=3.4.0; extra == "enterprise"
Requires-Dist: flask>=2.0.0; extra == "enterprise"
Requires-Dist: flask-jwt-extended>=4.0.0; extra == "enterprise"
Dynamic: author
Dynamic: home-page
Dynamic: license-file
Dynamic: requires-python
